setup.py
django_moat.egg-info/PKG-INFO
django_moat.egg-info/SOURCES.txt
django_moat.egg-info/dependency_links.txt
django_moat.egg-info/top_level.txt
example_project/main/__init__.py
example_project/main/models.py
example_project/main/tests.py
example_project/main/views.py
moat/__init__.py
moat/middleware.py