Metadata-Version: 1.0
Name: django-moat
Version: 0.1.1
Summary: django-moat
Home-page: http://amrox.github.com/django-moat/
Author: Andy Mroczkowski
Author-email: andy@mrox.net
License: UNKNOWN
Platform: any
